taggedartifacts/__init__.py
taggedartifacts/taggedartifacts.py
taggedartifacts-0.1.1.dist-info/LICENSE
taggedartifacts-0.1.1.dist-info/METADATA
taggedartifacts-0.1.1.dist-info/WHEEL
taggedartifacts-0.1.1.dist-info/top_level.txt
taggedartifacts-0.1.1.dist-info/RECORD
