Metadata-Version: 2.1
Name: taggedartifacts
Version: 0.1.1
Summary: Simple artifact versioning and caching for scientific workflows
Home-page: https://github.com/jisantuc/taggedartifacts
Author: James Santucci
Author-email: james.santucci@gmail.com
License: MIT license
Keywords: taggedartifacts
Platform: UNKNOWN
Classifier: Development Status :: 2 - Pre-Alpha
Classifier: Intended Audience :: Developers
Classifier: License :: OSI Approved :: MIT License
Classifier: Natural Language :: English
Classifier: Programming Language :: Python :: 2
Classifier: Programming Language :: Python :: 2.7
Classifier: Programming Language :: Python :: 3
Classifier: Programming Language :: Python :: 3.4
Classifier: Programming Language :: Python :: 3.5
Classifier: Programming Language :: Python :: 3.6
Classifier: Programming Language :: Python :: 3.7
Requires-Dist: pygit2 (==0.28.1)
